CHANGES.rst
MANIFEST.in
README.rst
setup.cfg
setup.py
collective/__init__.py
collective.depositbox.egg-info/PKG-INFO
collective.depositbox.egg-info/SOURCES.txt
collective.depositbox.egg-info/dependency_links.txt
collective.depositbox.egg-info/entry_points.txt
collective.depositbox.egg-info/namespace_packages.txt
collective.depositbox.egg-info/not-zip-safe
collective.depositbox.egg-info/requires.txt
collective.depositbox.egg-info/top_level.txt
collective/depositbox/README.txt
collective/depositbox/TODO.txt
collective/depositbox/__init__.py
collective/depositbox/adapter.py
collective/depositbox/browser.py
collective/depositbox/config.py
collective/depositbox/configure.zcml
collective/depositbox/data.pt
collective/depositbox/interfaces.py
collective/depositbox/store.py
collective/depositbox/tests.py
collective/depositbox/update_locales.sh
collective/depositbox/usage.rst
collective/depositbox/locales/collective.depositbox.pot
collective/depositbox/locales/nl/LC_MESSAGES/collective.depositbox.mo
collective/depositbox/locales/nl/LC_MESSAGES/collective.depositbox.po
collective/depositbox/sample/__init__.py
collective/depositbox/sample/browser.py
collective/depositbox/sample/configure.zcml
collective/depositbox/sample/templates/add.pt
collective/depositbox/sample/templates/confirm.pt
collective/depositbox/sample/templates/delete.pt
collective/depositbox/sample/templates/edit.pt
collective/depositbox/sample/templates/simple.pt
docs/INSTALL.txt
docs/LICENSE.GPL
docs/LICENSE.txt