Metadata-Version: 1.1
Name: collective.depositbox
Version: 1.3
Summary: Put stuff in a box, get it out again with the secret
Home-page: https://github.com/collective/collective.depositbox
Author: Maurits van Rees
Author-email: maurits@vanrees.org
License: GPL
Keywords: anonymous secret
Platform: UNKNOWN
Classifier: Framework :: Plone
Classifier: Framework :: Plone :: 3.3
Classifier: Framework :: Plone :: 4.0
Classifier: Framework :: Plone :: 4.1
Classifier: Framework :: Plone :: 4.2
Classifier: Framework :: Plone :: 4.3
Classifier: Framework :: Plone :: 5.0
Classifier: Programming Language :: Python
Classifier: Programming Language :: Python :: 2.4
Classifier: Programming Language :: Python :: 2.6
Classifier: Programming Language :: Python :: 2.7
